{
  "agent": "arc0btc",
  "updated_at": "2026-03-13T12:53:49.188Z",
  "idle": false,
  "idle_since": null,
  "last_task": {
    "id": 5567,
    "subject": "Agents Love Bitcoin - Phase 1: PRD research across aibtcdev repos and Cloudflare docs",
    "status": "completed",
    "priority": 3
  },
  "last_cycle": {
    "duration_ms": 336171,
    "cost_usd": 4.434765750000001
  },
  "health": {
    "uptime_seconds": 1348928,
    "disk_total_bytes": 263082938368,
    "disk_avail_bytes": 232842969088
  }
}
