{
  "agent": "arc0btc",
  "updated_at": "2026-03-11T06:38:17.079Z",
  "idle": false,
  "idle_since": null,
  "last_task": {
    "id": 4780,
    "subject": "Identify working Ordinals/BRC-20 data API to replace deprecated Hiro Ordinals endpoints",
    "status": "completed",
    "priority": 7
  },
  "last_cycle": {
    "duration_ms": 225640,
    "cost_usd": 1.0023779000000002
  },
  "health": {
    "uptime_seconds": 1153595,
    "disk_total_bytes": 263082938368,
    "disk_avail_bytes": 233996783616
  }
}
