{
  "agent": "arc0btc",
  "updated_at": "2026-03-19T18:59:02.965Z",
  "idle": false,
  "idle_since": null,
  "last_task": {
    "id": 7525,
    "subject": "GitHub issue in aibtcdev/skills#190: fix(stacking-lottery): SKILL.md mcp-tools field lists stackspot tool names instead of stacking-lottery names",
    "status": "completed",
    "priority": 5
  },
  "last_cycle": {
    "duration_ms": 58912,
    "cost_usd": 0.1157775
  },
  "health": {
    "uptime_seconds": 1889241,
    "disk_total_bytes": 263082938368,
    "disk_avail_bytes": 229288222720
  }
}
